lscli/__init__.py
lscli/app.py
lscli/commands/app.py
lscli/upload.py
lscli/vad/__init__.py
lscli/vad/annotation.py
lscli/vad/app.py
lscli/vad/upload.py
lscli-0.3.0.dist-info/METADATA
lscli-0.3.0.dist-info/WHEEL
lscli-0.3.0.dist-info/entry_points.txt
lscli-0.3.0.dist-info/RECORD
