Metadata-Version: 2.3
Name: lscli
Version: 0.3.0
Summary: 
Author: migo
Author-email: 1695587905@qq.com
Requires-Python: >=3.10,<3.13
Classifier: Programming Language :: Python :: 3
Classifier: Programming Language :: Python :: 3.10
Classifier: Programming Language :: Python :: 3.11
Classifier: Programming Language :: Python :: 3.12
Requires-Dist: imageio (>=2.37.0,<3.0.0)
Requires-Dist: label-studio-sdk (>=1.0.20,<2.0.0)
Requires-Dist: minio (>=7.2.16,<8.0.0)
Requires-Dist: numpy (==1.26.4)
Requires-Dist: pandas (>=2.3.1,<3.0.0)
Requires-Dist: pydantic (>=2.11.7,<3.0.0)
Requires-Dist: python-dotenv (>=1.1.1,<2.0.0)
Requires-Dist: typer (>=0.16.0,<0.17.0)
Requires-Dist: yarl (>=1.20.1,<2.0.0)
